simpleio.py
adafruit_circuitpython_simpleio-3.0.18.dist-info/licenses/LICENSE
adafruit_circuitpython_simpleio-3.0.18.dist-info/METADATA
adafruit_circuitpython_simpleio-3.0.18.dist-info/WHEEL
adafruit_circuitpython_simpleio-3.0.18.dist-info/top_level.txt
adafruit_circuitpython_simpleio-3.0.18.dist-info/RECORD
