Metadata-Version: 2.4
Name: adafruit-circuitpython-simpleio
Version: 3.0.18
Summary: CircuitPython helper library to simplify hardware interactions.
Author-email: Adafruit Industries <circuitpython@adafruit.com>
License: MIT
Project-URL: Homepage, https://github.com/adafruit/Adafruit_CircuitPython_SimpleIO
Keywords: adafruit,simpleio,servo,map,range,bitwrite,hardware,micropython,circuitpython
Classifier: Intended Audience :: Developers
Classifier: Topic :: Software Development :: Libraries
Classifier: Topic :: Software Development :: Embedded Systems
Classifier: Topic :: System :: Hardware
Classifier: License :: OSI Approved :: MIT License
Classifier: Programming Language :: Python :: 3
License-File: LICENSE
Requires-Dist: Adafruit-Blinka
Provides-Extra: optional
Dynamic: license-file
